test/__init__.py
test/your_lucky_song_test.py
your_lucky_song/__init__.py
your_lucky_song-0.0.0.dist-info/METADATA
your_lucky_song-0.0.0.dist-info/WHEEL
your_lucky_song-0.0.0.dist-info/top_level.txt
your_lucky_song-0.0.0.dist-info/RECORD
