Metadata-Version: 2.1
Name: your-lucky-song
Version: 0.0.0
Summary: A python package for finding song on the day you were born
Home-page: https://github.com/linzhou-zhong/your_lucky_song
Author: Linzhou ZHONG
Author-email: justgiveacar@gmail.com
License: MIT
Platform: UNKNOWN
Requires-Dist: requests
Requires-Dist: beautifulsoup4
Requires-Dist: setuptools
Requires-Dist: datetime
